sevk/__init__.py
sevk/client.py
sevk/markup/__init__.py
sevk/markup/renderer.py
sevk/resources/__init__.py
sevk/resources/audiences.py
sevk/resources/broadcasts.py
sevk/resources/contacts.py
sevk/resources/domains.py
sevk/resources/emails.py
sevk/resources/segments.py
sevk/resources/subscriptions.py
sevk/resources/templates.py
sevk/resources/topics.py
sevk-0.0.1.dist-info/METADATA
sevk-0.0.1.dist-info/WHEEL
sevk-0.0.1.dist-info/top_level.txt
sevk-0.0.1.dist-info/RECORD
