Metadata-Version: 2.4
Name: sevk
Version: 0.0.1
Summary: Python SDK for Sevk API
Author-email: Sevk <dev@sevk.io>
License: MIT
Project-URL: Homepage, https://sevk.io
Project-URL: Documentation, https://docs.sevk.io
Project-URL: Repository, https://github.com/sevk-io/sevk-python
Keywords: sevk,email,api,sdk
Classifier: Development Status :: 3 - Alpha
Classifier: Intended Audience :: Developers
Classifier: License :: OSI Approved :: MIT License
Classifier: Programming Language :: Python :: 3
Classifier: Programming Language :: Python :: 3.8
Classifier: Programming Language :: Python :: 3.9
Classifier: Programming Language :: Python :: 3.10
Classifier: Programming Language :: Python :: 3.11
Classifier: Programming Language :: Python :: 3.12
Requires-Python: >=3.8
Requires-Dist: httpx>=0.24.0
Provides-Extra: dev
Requires-Dist: pytest>=7.0.0; extra == "dev"
Requires-Dist: pytest-asyncio>=0.21.0; extra == "dev"
Requires-Dist: python-dotenv>=1.0.0; extra == "dev"
